cr_utils/__init__.py
cr_utils/costmanager.py
cr_utils/llm.py
cr_utils/logger.py
cr_utils/protocol.py
cr_utils/register.py
cr_utils/singleton.py
cr_utils/function/__init__.py
cr_utils/function/files.py
cr_utils/function/image.py
cr_utils/function/make.py
cr_utils/function/text.py
cr_utils/locks/__init__.py
cr_utils/locks/rw.py
cr_utils-0.3.1.dist-info/licenses/LICENSE.md
cr_utils-0.3.1.dist-info/METADATA
cr_utils-0.3.1.dist-info/WHEEL
cr_utils-0.3.1.dist-info/top_level.txt
cr_utils-0.3.1.dist-info/RECORD
