Metadata-Version: 2.4
Name: cr_utils
Version: 0.3.1
Summary: 一个实用工具库，包含日志管理、单例模式、注册表、成本管理、多功能函数和数据协议等模块，帮助你快速构建和管理 Python 项目。
Author-email: Rong Cheng <chengrong@tju.edu.cn>
License: MIT License
Project-URL: Homepage, https://github.com/cbxgss/cr_utils
Requires-Python: >=3.9
License-File: LICENSE.md
Requires-Dist: litellm>=1.58.4
Requires-Dist: omegaconf>=2.3.0
Requires-Dist: openai>=1.74.0
Requires-Dist: pandas>=2.2.3
Requires-Dist: psutil>=7.0.0
Requires-Dist: tenacity>=9.1.2
Requires-Dist: prettytable>=3.16.0
Requires-Dist: ipdb>=0.13.13
Requires-Dist: setuptools>=80.9.0
Requires-Dist: zstandard>=0.23.0
Dynamic: license-file
